lindh/jsondb/__init__.py
lindh/jsondb/csv.py
lindh_jsondb-0.3.0.dist-info/LICENSE
lindh_jsondb-0.3.0.dist-info/METADATA
lindh_jsondb-0.3.0.dist-info/WHEEL
lindh_jsondb-0.3.0.dist-info/top_level.txt
lindh_jsondb-0.3.0.dist-info/RECORD
