Metadata-Version: 2.1
Name: lindh-jsondb
Version: 0.3.0
Summary: JSON based document database
Home-page: https://github.com/eblade/jsondb
Author: Johan Egneblad
Author-email: johan@DELETEMEegneblad.se
License: MIT
Download-URL: https://github.com/eblade/jsondb/archive/v0.3.0.tar.gz
Platform: UNKNOWN
Classifier: Programming Language :: Python :: 3
Classifier: Operating System :: OS Independent
Classifier: Development Status :: 4 - Beta
Classifier: Intended Audience :: Developers
Classifier: License :: OSI Approved :: MIT License
Requires-Dist: blist (>=1.3.6)
